gauge/__init__.py
gauge/cli/__init__.py
gauge/cli/console.py
gauge/cli/deploy.py
gauge/cli/main.py
gauge/cli/tests/__init__.py
gauge/cli/tests/sample.py
gauge/cli/tests/test_deploy.py
gauge/cli/tests/test_main.py
gauge/sdk/__init__.py
gauge/sdk/config.py
gauge/sdk/main.py
gauge/sdk/tests/__init__.py
gauge/sdk/tests/test_sdk.py
tine-0.0.5.dist-info/METADATA
tine-0.0.5.dist-info/WHEEL
tine-0.0.5.dist-info/entry_points.txt
tine-0.0.5.dist-info/top_level.txt
tine-0.0.5.dist-info/RECORD
